{
  "mood_sad": {
    "precision": 1.0,
    "recall": 1.0,
    "f1-score": 1.0,
    "support": 6,
    "confused_with": {}
  },
  "inform_condition": {
    "precision": 1.0,
    "recall": 1.0,
    "f1-score": 1.0,
    "support": 6,
    "confused_with": {}
  },
  "hypertension_prevention": {
    "precision": 1.0,
    "recall": 1.0,
    "f1-score": 1.0,
    "support": 4,
    "confused_with": {}
  },
  "mood_great": {
    "precision": 1.0,
    "recall": 1.0,
    "f1-score": 1.0,
    "support": 6,
    "confused_with": {}
  },
  "manage_condition_hypertension": {
    "precision": 1.0,
    "recall": 1.0,
    "f1-score": 1.0,
    "support": 3,
    "confused_with": {}
  },
  "affirm": {
    "precision": 1.0,
    "recall": 1.0,
    "f1-score": 1.0,
    "support": 6,
    "confused_with": {}
  },
  "mental_health_support": {
    "precision": 1.0,
    "recall": 1.0,
    "f1-score": 1.0,
    "support": 3,
    "confused_with": {}
  },
  "greet": {
    "precision": 1.0,
    "recall": 1.0,
    "f1-score": 1.0,
    "support": 6,
    "confused_with": {}
  },
  "monitor_condition_diabetes": {
    "precision": 1.0,
    "recall": 1.0,
    "f1-score": 1.0,
    "support": 3,
    "confused_with": {}
  },
  "diabetes_prevention": {
    "precision": 1.0,
    "recall": 1.0,
    "f1-score": 1.0,
    "support": 4,
    "confused_with": {}
  },
  "monitor_condition_hypertension": {
    "precision": 1.0,
    "recall": 1.0,
    "f1-score": 1.0,
    "support": 2,
    "confused_with": {}
  },
  "manage_condition_diabetes": {
    "precision": 1.0,
    "recall": 1.0,
    "f1-score": 1.0,
    "support": 4,
    "confused_with": {}
  },
  "accuracy": 1.0,
  "macro avg": {
    "precision": 1.0,
    "recall": 1.0,
    "f1-score": 1.0,
    "support": 53
  },
  "weighted avg": {
    "precision": 1.0,
    "recall": 1.0,
    "f1-score": 1.0,
    "support": 53
  },
  "micro avg": {
    "precision": 1.0,
    "recall": 1.0,
    "f1-score": 1.0,
    "support": 53
  }
}